cci_calculator/__init__.py
cci_calculator/calc.py
cci_calculator/codes.json
cci_calculator-0.1.3.dist-info/LICENSE
cci_calculator-0.1.3.dist-info/METADATA
cci_calculator-0.1.3.dist-info/WHEEL
cci_calculator-0.1.3.dist-info/top_level.txt
cci_calculator-0.1.3.dist-info/RECORD
