Metadata-Version: 2.1
Name: cci-calculator
Version: 0.1.3
Summary: Charlson Comorbidity Index calculator
Home-page: https://github.com/psokolo/cci/tree/main/cci_calculator
Author-email: sokol.to@gmail.com
License: MIT
Classifier: Programming Language :: Python :: 3
Classifier: License :: OSI Approved :: MIT License
Classifier: Operating System :: OS Independent
Requires-Python: >=3.6
License-File: LICENSE
